copyright_free_songs/__init__.py
copyright_free_songs-1767774.444.65.dist-info/licenses/LICENSE
copyright_free_songs-1767774.444.65.dist-info/METADATA
copyright_free_songs-1767774.444.65.dist-info/WHEEL
copyright_free_songs-1767774.444.65.dist-info/top_level.txt
copyright_free_songs-1767774.444.65.dist-info/RECORD
