Metadata-Version: 2.4
Name: copyright-free-songs
Version: 1767774.444.65
Summary: High-quality integration for https://supermaker.ai/music/copyright-free-songs/
Home-page: https://supermaker.ai/music/copyright-free-songs/
Author: SuperMaker
Classifier: Programming Language :: Python :: 3
Classifier: License :: OSI Approved :: MIT License
Requires-Python: >=3.6
License-File: LICENSE
Dynamic: author
Dynamic: classifier
Dynamic: description
Dynamic: description-content-type
Dynamic: home-page
Dynamic: license-file
Dynamic: requires-python
Dynamic: summary
